audio_connector_sdk/__init__.py
audio_connector_sdk/vonage_video/__init__.py
audio_connector_sdk/vonage_video/errors.py
audio_connector_sdk/vonage_video/video.py
audio_connector_sdk/vonage_video/core/__init__.py
audio_connector_sdk/vonage_video/core/audio_connector_connection.py
audio_connector_sdk/vonage_video/core/audio_connector_server.py
audio_connector_sdk/vonage_video/models/__init__.py
audio_connector_sdk/vonage_video/models/audio_connector.py
vonage_audio_connector_server-0.1.1.dist-info/licenses/LICENSE
vonage_audio_connector_server-0.1.1.dist-info/METADATA
vonage_audio_connector_server-0.1.1.dist-info/WHEEL
vonage_audio_connector_server-0.1.1.dist-info/top_level.txt
vonage_audio_connector_server-0.1.1.dist-info/RECORD
