Metadata-Version: 2.4
Name: vonage-audio-connector-server
Version: 0.1.1
Summary: Vonage Audio Connector Server SDK
Author-email: Vonage <devrel@vonage.com>
License:                                  Apache License
Project-URL: Repository, https://github.com/opentok/audio-connector-server-sdk
Project-URL: Issues, https://github.com/opentok/audio-connector-server-sdk/issues
Classifier: Programming Language :: Python
Classifier: Programming Language :: Python :: 3.9
Classifier: Programming Language :: Python :: 3.10
Classifier: Programming Language :: Python :: 3.11
Classifier: Programming Language :: Python :: 3.12
Classifier: License :: OSI Approved :: Apache Software License
Requires-Python: >=3.9
License-File: LICENSE
Requires-Dist: pydantic~=2.11.7
Requires-Dist: websockets~=15.0
Requires-Dist: asyncio~=4.0.0
Requires-Dist: pytest~=8.4.1
Requires-Dist: pytest-asyncio~=1.2.0
Dynamic: license-file
